lamin/__init__.py
lamin/dev.py
lamin-0.2.1.dist-info/WHEEL
lamin-0.2.1.dist-info/METADATA
lamin-0.2.1.dist-info/RECORD
